[
    {
        "accuracy": 0.8306,
        "batch": 128,
        "duration": 2212395266472,
        "lr": 0.008696024734839457,
        "momentum": 0.8932373290094291,
        "transform": "norm_299",
        "uid": "266376241105341888b892ac5d7e1488"
    },
    {
        "accuracy": 0.7612,
        "batch": 128,
        "duration": 97538403125,
        "lr": 0.044987810128409536,
        "momentum": 0.7402701788426475,
        "transform": "norm_32",
        "uid": "c2582c51085160aa31f49bd33378a60c"
    },
    {
        "accuracy": 0.5979,
        "batch": 512,
        "duration": 76899310464,
        "lr": 0.038341669900570835,
        "momentum": 0.0736281348578206,
        "transform": "norm",
        "uid": "3d30e40f2eee36e8b80cd21d6deb8644"
    },
    {
        "accuracy": 0.544,
        "batch": 32,
        "duration": 13990420953326,
        "lr": 0.0005203989313272982,
        "momentum": 0.4372425481210179,
        "transform": "soft_pad",
        "uid": "273081dcb767c3ff5c68cfb2c59ca28c"
    },
    {
        "accuracy": 0.3801,
        "batch": 128,
        "duration": 5968281566350,
        "lr": 0.00015191316356651138,
        "momentum": 0.0284984788825835,
        "transform": "echo_512",
        "uid": "784a815c837d3012f5bc8f7a8be1910d"
    }
]