[
    {
        "accuracy": 0.9861,
        "batch": 2,
        "duration": 1279041330824,
        "lr": 0.02902790252170875,
        "momentum": 0.7325153794835008,
        "transform": "norm_32_flip",
        "uid": "b4dd3448-57bd-4c3f-ab21-7237dde263b4"
    },
    {
        "accuracy": 0.9811,
        "batch": 2,
        "duration": 1280392082036,
        "lr": 0.12342851965547155,
        "momentum": 0.4903587317255893,
        "transform": "norm_32",
        "uid": "dc8e9ee8-29b7-4507-83cf-39f08f34f4ad"
    }
]