[
    {
        "accuracy": 0.9315699829676385,
        "batch": 8,
        "duration": 39550952684,
        "lr": 0.05328455474800104,
        "momentum": 0.05844273082030149,
        "transform": "echo_32_flip",
        "uid": "ddbed6d557d567fca47d94f9a15b85d6"
    },
    {
        "accuracy": 0.916491333533714,
        "batch": 64,
        "duration": 90387473544,
        "lr": 0.16191052769030673,
        "momentum": 0.6431300039368911,
        "transform": "norm_32_flip",
        "uid": "f9545a38b761d9bfb6780997af01b507"
    },
    {
        "accuracy": 0.8925458370904719,
        "batch": 128,
        "duration": 79851293506,
        "lr": 0.7959647597403292,
        "momentum": 0.6514342279029792,
        "transform": "norm_32_flip",
        "uid": "70049821082c7c47081fc2c082fba288"
    },
    {
        "accuracy": 0.8773669972948602,
        "batch": 16,
        "duration": 118808846363,
        "lr": 0.00482923136379444,
        "momentum": 0.7824425860555365,
        "transform": "echo_64",
        "uid": "dffc973e674b2ef61919f9b4008a8cf1"
    },
    {
        "accuracy": 0.8311291453762149,
        "batch": 64,
        "duration": 675255095454,
        "lr": 0.025925793209739447,
        "momentum": 0.24925033172537248,
        "transform": "echo_flip",
        "uid": "9229b3880f55c3058422dbbd3719fbe7"
    },
    {
        "accuracy": 0.8280232441639115,
        "batch": 64,
        "duration": 32217425392,
        "lr": 0.0028465837796274943,
        "momentum": 0.18493011816745353,
        "transform": "echo_32_flip",
        "uid": "be301ca6bd9f01cac26b5d84ca5b6e58"
    },
    {
        "accuracy": 0.8094379320709347,
        "batch": 64,
        "duration": 96980518215,
        "lr": 0.002275332516752927,
        "momentum": 0.27373658412651525,
        "transform": "norm_64",
        "uid": "462d283bcf1404d44feb1c156399ae6e"
    },
    {
        "accuracy": 0.7824867247770765,
        "batch": 256,
        "duration": 39432110261,
        "lr": 0.004196983767630851,
        "momentum": 0.44862411270078584,
        "transform": "norm_64_flip",
        "uid": "38f54a2260a116e4a76e0d3d611e3586"
    },
    {
        "accuracy": 0.7599939885782988,
        "batch": 4,
        "duration": 315647888980,
        "lr": 6.236461707998436e-05,
        "momentum": 0.633212371727291,
        "transform": "norm_32_flip",
        "uid": "d33a5edaecc0c190ef34fa2ad540089b"
    },
    {
        "accuracy": 0.7419096282937582,
        "batch": 128,
        "duration": 102932337225,
        "lr": 0.2614422280773536,
        "momentum": 0.7094792931998506,
        "transform": "echo_128_flip",
        "uid": "68ab462e3369033889169375bb39f319"
    },
    {
        "accuracy": 0.740657248772668,
        "batch": 16,
        "duration": 38363713642,
        "lr": 0.016960300550648143,
        "momentum": 0.2802381009641516,
        "transform": "norm_32_flip",
        "uid": "b7c6a399d4ff98c0b98b103a519bf463"
    },
    {
        "accuracy": 0.7204688908926962,
        "batch": 64,
        "duration": 87700847630,
        "lr": 0.0001939060636154223,
        "momentum": 0.6827413385679164,
        "transform": "norm_32",
        "uid": "873d3737769165200e48757c8f0ee9de"
    },
    {
        "accuracy": 0.7111010920749424,
        "batch": 64,
        "duration": 576479364042,
        "lr": 0.000177723430595117,
        "momentum": 0.8075176390913811,
        "transform": "echo_299_flip",
        "uid": "a394d59555b2bfd09fa5649f05d9579e"
    },
    {
        "accuracy": 0.7029355775974351,
        "batch": 8,
        "duration": 168497979519,
        "lr": 0.08250699022880935,
        "momentum": 0.7087602986515636,
        "transform": "echo_64_flip",
        "uid": "493aaa162c9e0290bdfa61aab6e9e6f7"
    },
    {
        "accuracy": 0.6666666666666666,
        "batch": 64,
        "duration": 254468335550,
        "lr": 0.02484412978878238,
        "momentum": 0.9252052435628627,
        "transform": "echo_flip",
        "uid": "fe4a6a0c70470a5cb4fb997961101ad8"
    },
    {
        "accuracy": 0.6328524195972347,
        "batch": 16,
        "duration": 376711673741,
        "lr": 1.8767546514721212e-05,
        "momentum": 0.049824155681157944,
        "transform": "echo_256",
        "uid": "f773dff97a44bf0f655467fd109d9187"
    }
]