[
    {
        "accuracy": 0.8475,
        "batch": 4,
        "duration": 6541794560293,
        "lr": 0.0061,
        "momentum": 0.7549,
        "transform": "norm_299",
        "uid": "45409920-be3d-4fb8-a950-bd60f4e97c28"
    },
    {
        "accuracy": 0.8416,
        "batch": 4,
        "duration": 10073610983803,
        "lr": 0.0068981913970451005,
        "momentum": 0.3191714522590947,
        "transform": "norm_512",
        "uid": "6fb0b7b5-fe73-40b0-805c-fca7d4182aa1"
    },
    {
        "accuracy": 0.6165,
        "batch": 1024,
        "duration": 97217416102,
        "lr": 0.4341568476753592,
        "momentum": 0.09828304592709958,
        "transform": "norm_flip",
        "uid": "8bb7c1aa-5ca9-495f-98de-ef0a961ec493"
    }
]