[
    {
        "accuracy": 0.7403821656050955,
        "batch": 8,
        "dropout": 0.01821075383730636,
        "duration": 786214427201,
        "lr": 0.40129360508984696,
        "momentum": 0.006236483477023547,
        "transform": "norm_128_flip",
        "uid": "a8f5dcf8-c7f5-42cc-8abb-b6af2312b05b"
    },
    {
        "accuracy": 0.378343949044586,
        "batch": 16,
        "dropout": 0.037900449512628276,
        "duration": 902318226511,
        "lr": 0.0021174857229790353,
        "momentum": 0.6527875782853685,
        "transform": "echo_299_flip",
        "uid": "f225a843-39d1-446c-94ab-cb9024a4515a"
    }
]