[
    {
        "accuracy": 0.2407,
        "batch": 4,
        "dropout": 0.08112859905364583,
        "duration": 521620926461,
        "lr": 0.0033129211193824934,
        "momentum": 0.9630685024761649,
        "norm_eps": 0.16469296249135046,
        "norm_momentum": 0.4336004961877049,
        "transform": "echo_128",
        "uid": "ef309165-a099-4751-856f-d45c8d538029"
    },
    {
        "accuracy": 0.1692,
        "batch": 8,
        "dropout": 0.36486089545659295,
        "duration": 116567074348,
        "lr": 0.043410446153840654,
        "momentum": 0.34139072342020516,
        "norm_eps": 0.07809404157206912,
        "norm_momentum": 0.3593218678995783,
        "transform": "norm_32",
        "uid": "54e5d9cd-ec7a-4bc2-9381-1f3b07de7fe2"
    },
    {
        "accuracy": 0.1592,
        "batch": 16,
        "dropout": 0.29061680574642274,
        "duration": 60531970283,
        "lr": 0.028452701359314582,
        "momentum": 0.5756135392273866,
        "norm_eps": 0.06178363364753925,
        "norm_momentum": 0.8850021082871623,
        "transform": "norm",
        "uid": "6b1d3ef2-97ae-483c-ae67-86dd50a409fc"
    },
    {
        "accuracy": 0.0171,
        "batch": 512,
        "dropout": 0.08101705692221889,
        "duration": 21789936378,
        "lr": 0.10512482867823404,
        "momentum": 0.17708154948734844,
        "norm_eps": 0.07991738920922375,
        "norm_momentum": 0.3042592267545683,
        "transform": "echo_64",
        "uid": "14d8ac54-1a3c-486e-8117-a68cbec8a2cb"
    },
    {
        "accuracy": 0.0154,
        "batch": 128,
        "dropout": 0.2723029719231244,
        "duration": 332042458726,
        "lr": 0.0005345853827699101,
        "momentum": 0.22144896406447112,
        "norm_eps": 0.020512823500908828,
        "norm_momentum": 0.5715875893529476,
        "transform": "echo_299_flip",
        "uid": "5a71ffa6-307b-4d4b-9025-8de29de448ea"
    },
    {
        "accuracy": 0.0154,
        "batch": 4,
        "dropout": 0.20649718379146081,
        "duration": 448637414763,
        "lr": 0.00019553375148388322,
        "momentum": 0.12554997632194345,
        "norm_eps": 0.1155120518705538,
        "norm_momentum": 0.9682939761491927,
        "transform": "norm_299",
        "uid": "a4ba1324-3ab3-4ca2-978b-dbf9c59ece7c"
    }
]