[
    {
        "accuracy": 0.987,
        "batch": 16,
        "duration": 369131918524,
        "lr": 0.08345876704754737,
        "momentum": 0.3206638492460989,
        "transform": "echo_32",
        "uid": "c7676eaf-54af-4e7c-8c9c-bccebb852f62"
    },
    {
        "accuracy": 0.981,
        "batch": 32,
        "duration": 205482279046,
        "lr": 0.015857943123351734,
        "momentum": 0.03406599367521379,
        "transform": "echo_32_flip",
        "uid": "998b7f23-dae7-4193-b593-3b4c8ace081b"
    },
    {
        "accuracy": 0.9491,
        "batch": 2,
        "duration": 2579008707210,
        "lr": 0.0002918503372780411,
        "momentum": 0.4546534901333966,
        "transform": "norm_32_flip",
        "uid": "d17e6062-264b-4e55-a329-9a2c8be6c67a"
    }
]