[
    {
        "accuracy": 0.9414950829748002,
        "batch": 4,
        "dropout": 0.11539453684353285,
        "duration": 1524319263050,
        "lr": 0.015031006956215957,
        "momentum": 0.30174352470409915,
        "transform": "norm_128",
        "uid": "e116e6d8-fd79-4ec4-b275-0d12fd217c00"
    },
    {
        "accuracy": 0.9111478180700676,
        "batch": 16,
        "dropout": 0.24559156199686594,
        "duration": 5560437288204,
        "lr": 0.2651281807375264,
        "momentum": 0.15289248932535993,
        "transform": "echo_512_flip",
        "uid": "1ebfd882-2680-4a48-88ed-db1eb619f63b"
    },
    {
        "accuracy": 0.8892901044867855,
        "batch": 8,
        "dropout": 0.0723761134458294,
        "duration": 1313713747844,
        "lr": 0.01488423700710049,
        "momentum": 0.12243223327461805,
        "transform": "norm_299_flip",
        "uid": "bdf7c0ab-6220-4428-9863-0a2f2e1e4daf"
    },
    {
        "accuracy": 0.875460971112477,
        "batch": 16,
        "dropout": 0.31186918789327944,
        "duration": 5557560549049,
        "lr": 0.011048274412181583,
        "momentum": 0.8004764355324845,
        "transform": "echo_512_flip",
        "uid": "30134903-92a0-4dff-a5b6-2feeb0923905"
    },
    {
        "accuracy": 0.8747311001843885,
        "batch": 128,
        "dropout": 0.04297338258010458,
        "duration": 1296238533595,
        "lr": 0.6880714667889599,
        "momentum": 0.5739340857623462,
        "transform": "norm",
        "uid": "0c4a7854-f179-4ec2-b8d5-21c2f484a31b"
    },
    {
        "accuracy": 0.8557160417947142,
        "batch": 2,
        "dropout": 0.41654315479616755,
        "duration": 3744783384237,
        "lr": 0.540616271651717,
        "momentum": 0.1353207718074475,
        "transform": "norm_256_flip",
        "uid": "d567a211-741e-4604-a9f3-f4eda7c1cb8b"
    },
    {
        "accuracy": 0.3195298094652735,
        "batch": 4,
        "dropout": 0.19850496578017052,
        "duration": 1641708433642,
        "lr": 0.0016376838412642313,
        "momentum": 0.39525185381126804,
        "transform": "echo_299_flip",
        "uid": "5986e9be-e4f1-4c2f-ade7-ecf80c209ee1"
    },
    {
        "accuracy": 0.2959818684695759,
        "batch": 32,
        "dropout": 0.09906250553812268,
        "duration": 3524151569454,
        "lr": 0.0008061213114865953,
        "momentum": 0.5647359150705937,
        "transform": "norm_299_flip",
        "uid": "9ad379bc-3dc5-411c-aa25-3cac02ed2d6b"
    },
    {
        "accuracy": 0.2783881376767056,
        "batch": 8,
        "dropout": 0.29070486251474753,
        "duration": 3360246261268,
        "lr": 0.0013472937615371273,
        "momentum": 0.6424424311670262,
        "transform": "norm_512_flip",
        "uid": "57d5ef90-4a80-413a-8b8b-0dabe221af42"
    },
    {
        "accuracy": 0.1988322065150584,
        "batch": 8,
        "dropout": 0.29009562176947135,
        "duration": 751120395085,
        "lr": 0.00028208693863373397,
        "momentum": 0.22236158617594415,
        "transform": "echo_64_flip",
        "uid": "b241c325-7c83-4fea-bf4a-21004d9b289e"
    },
    {
        "accuracy": 0.19387676705593115,
        "batch": 8,
        "dropout": 0.299256901690631,
        "duration": 1325432278599,
        "lr": 2.1752722002240608e-05,
        "momentum": 0.6573384561052301,
        "transform": "echo_299",
        "uid": "c2ab93fd-1467-4e2d-b397-61d66c406799"
    }
]