[
    {
        "accuracy": 0.2843312101910828,
        "batch": 1,
        "duration": 47646407619,
        "lr": 0.003285773259868539,
        "momentum": 0.8853191358127644,
        "transform": "norm_flip",
        "uid": "61505bc542597dc8aa63efcae987abc7"
    },
    {
        "accuracy": 0.27261146496815286,
        "batch": 1,
        "duration": 19093022312,
        "lr": 0.012164983235995753,
        "momentum": 0.8716958497459144,
        "transform": "norm_64_flip",
        "uid": "69b1d576373c2d30cf7c723ee2ac3f41"
    },
    {
        "accuracy": 0.2631847133757962,
        "batch": 32,
        "duration": 20051421786,
        "lr": 0.06826182397844609,
        "momentum": 0.667477170728024,
        "transform": "norm_256_flip",
        "uid": "edd92ddcb11c6064bde809838ef63b91"
    },
    {
        "accuracy": 0.23617834394904458,
        "batch": 64,
        "duration": 14801417949,
        "lr": 0.2767500956281185,
        "momentum": 0.11426199148390581,
        "transform": "norm_128_flip",
        "uid": "61b440df1b0001857dcf345a8eedbfac"
    },
    {
        "accuracy": 0.23388535031847132,
        "batch": 4,
        "duration": 44165295709,
        "lr": 0.027557501798128582,
        "momentum": 0.8912358148610133,
        "transform": "echo_512_flip",
        "uid": "6022db543a43c3902b101564239f1a08"
    },
    {
        "accuracy": 0.17987261146496816,
        "batch": 4,
        "duration": 15014972696,
        "lr": 0.043275152642980506,
        "momentum": 0.13906176104932289,
        "transform": "echo_128",
        "uid": "75a55b340b58f4da637dc0ea4fd1f4a7"
    },
    {
        "accuracy": 0.16993630573248408,
        "batch": 8,
        "duration": 18675142434,
        "lr": 0.05330570456925,
        "momentum": 0.7917551885980236,
        "transform": "echo_256",
        "uid": "f7fc23e0e36ef0aa71013d35a5360fa8"
    },
    {
        "accuracy": 0.16560509554140126,
        "batch": 64,
        "duration": 50651683604,
        "lr": 0.18925203382017233,
        "momentum": 0.3163334830216029,
        "transform": "complex_512",
        "uid": "439fb0756c1a05f507d209bade876a9f"
    },
    {
        "accuracy": 0.15694267515923566,
        "batch": 2,
        "duration": 16198526829,
        "lr": 0.010407271419962177,
        "momentum": 0.9729594775115192,
        "transform": "echo_128_flip",
        "uid": "2fcdd06b7baeb1e5b4a2380199704002"
    },
    {
        "accuracy": 0.1559235668789809,
        "batch": 512,
        "duration": 15086189450,
        "lr": 0.002534169975483693,
        "momentum": 0.596492213157327,
        "transform": "norm_128",
        "uid": "db0d5528e51be2a5723371572ec92cea"
    },
    {
        "accuracy": 0.15566878980891719,
        "batch": 16,
        "duration": 19792623279,
        "lr": 0.3860692352378551,
        "momentum": 0.5383174544100875,
        "transform": "echo_299_flip",
        "uid": "e840025072ef9cea95cd137c91e4d89f"
    },
    {
        "accuracy": 0.13630573248407643,
        "batch": 32,
        "duration": 12838729433,
        "lr": 0.005781294071010245,
        "momentum": 0.7124966078529789,
        "transform": "norm_64_flip",
        "uid": "af5189843f25ae8697c5fc7a0b369f2a"
    },
    {
        "accuracy": 0.12560509554140128,
        "batch": 16,
        "duration": 12903661739,
        "lr": 0.6920104013686161,
        "momentum": 0.5200399839564286,
        "transform": "complex_64_flip",
        "uid": "165022be1a9f511470c3ad839baf4c31"
    }
]