[
    {
        "accuracy": 0.4447,
        "attention_dropout": 0.5901884000200077,
        "batch": 16,
        "dropout": 0.4541475472576041,
        "duration": 5472786088390,
        "lr": 0.012623792051620005,
        "momentum": 0.11966041551338213,
        "stochastic_depth_prob": 0.23727529243486278,
        "transform": "echo_256",
        "uid": "7a7a1559-860d-43e2-9486-b16c603827e8"
    },
    {
        "accuracy": 0.1609,
        "attention_dropout": 0.5245846686190493,
        "batch": 4,
        "dropout": 0.035541935410035363,
        "duration": 22156862428563,
        "lr": 0.0035651858979172737,
        "momentum": 0.46834501404973217,
        "stochastic_depth_prob": 0.9074800497150685,
        "transform": "echo_512_flip",
        "uid": "bf493ebf-4877-4da7-861d-d3f955d8c366"
    }
]