[
    {
        "accuracy": 0.37707006369426754,
        "batch": 4,
        "duration": 1639335918998,
        "lr": 0.10824848102154176,
        "momentum": 0.61714066912767,
        "transform": "echo_256_flip",
        "uid": "542e88f2-17f5-42fd-a0af-46c2b2a12bb3"
    },
    {
        "accuracy": 0.3243312101910828,
        "batch": 8,
        "duration": 1050452221844,
        "lr": 0.45913575841099674,
        "momentum": 0.045250581009089075,
        "transform": "norm_512_flip",
        "uid": "f5e69088-8550-4d5a-b6ab-11576a366f3b"
    },
    {
        "accuracy": 0.19668789808917198,
        "batch": 512,
        "duration": 75102026615,
        "lr": 0.00030981467194555437,
        "momentum": 0.8688559332111546,
        "transform": "norm_64",
        "uid": "1f761132-1365-474c-a7c4-0929280cc78b"
    }
]