[
    {
        "accuracy": 0.4272611464968153,
        "batch": 512,
        "duration": 346609354794,
        "lr": 0.02019196991316703,
        "momentum": 0.1349215243207973,
        "transform": "norm_299_flip",
        "uid": "12b703d820a8820e3bf8e9851abbf221"
    },
    {
        "accuracy": 0.25630573248407645,
        "batch": 128,
        "duration": 199967466012,
        "lr": 0.00017901662077915247,
        "momentum": 0.658883267509121,
        "transform": "echo_128",
        "uid": "85dbfc6d1d977179ed48ee6ea8c6d380"
    }
]