[
    {
        "accuracy": 0.1933080404996872,
        "batch": 256,
        "duration": 13368680626332,
        "lr": 0.06658686532589715,
        "momentum": 0.3771130126567359,
        "transform": "echo_32",
        "uid": "860529e4-672f-4bc7-a034-f34c4467f3b3"
    },
    {
        "accuracy": 0.15207381546497345,
        "batch": 4,
        "duration": 15159417388791,
        "lr": 0.0010816724245831693,
        "momentum": 0.956364811707963,
        "transform": "norm_128",
        "uid": "96b117ec-7e43-465f-93e3-b9663a76cd38"
    }
]