[
    {
        "accuracy": 0.6881528662420382,
        "batch": 16,
        "duration": 593106581241,
        "lr": 0.0013387782177441696,
        "momentum": 0.8800081764540776,
        "transform": "echo_299_flip",
        "uid": "ec61f259804e937f7c122adb4cbc1f4c"
    },
    {
        "accuracy": 0.5877707006369427,
        "batch": 32,
        "duration": 411995772404,
        "lr": 0.003477355128550615,
        "momentum": 0.8047299715167439,
        "transform": "echo_128_flip",
        "uid": "53c6d9013748bd67faff32b2fa6addac"
    }
]