[
    {
        "accuracy": 0.5425,
        "batch": 256,
        "dropout": 0.4327388544785537,
        "duration": 313860891259,
        "lr": 0.0025132710709096706,
        "momentum": 0.3234450675616647,
        "transform": "echo_64",
        "uid": "0e34c0d9-e5b5-4767-941a-8424039da267"
    },
    {
        "accuracy": 0.5234,
        "batch": 16,
        "dropout": 0.04121304828022232,
        "duration": 1288991648084,
        "lr": 0.001302414949728489,
        "momentum": 0.13794729798018102,
        "transform": "norm_512",
        "uid": "6ddc6194-aec1-4782-829c-cefca6912b8f"
    },
    {
        "accuracy": 0.495,
        "batch": 512,
        "dropout": 0.9974739173920845,
        "duration": 558405518752,
        "lr": 0.0010947515513478501,
        "momentum": 0.8886257305082055,
        "transform": "norm_299",
        "uid": "5236af0b-7c54-4a6a-b988-7c06b87e82c3"
    },
    {
        "accuracy": 0.4608,
        "batch": 1,
        "dropout": 0.29472554689837593,
        "duration": 2505903019077,
        "lr": 0.0025341582405086875,
        "momentum": 0.10128729628328392,
        "transform": "norm_64",
        "uid": "b7169a07-761f-4fc1-a7ec-4c37921ed681"
    },
    {
        "accuracy": 0.2973,
        "batch": 2,
        "dropout": 0.0884193295291184,
        "duration": 1344239406414,
        "lr": 4.8992027531726764e-05,
        "momentum": 0.4837516899598263,
        "transform": "echo_299",
        "uid": "8732bf19-36b9-43e7-812b-22cd8924c5e2"
    }
]