[
    {
        "accuracy": 0.712,
        "batch": 4,
        "dropout": 0.21123708715517148,
        "duration": 7148005300640,
        "lr": 0.04932342393273471,
        "momentum": 0.8364030728415338,
        "transform": "echo_512",
        "uid": "57726e7dd5712f46b913fb0bbe954fad"
    },
    {
        "accuracy": 0.6978,
        "batch": 64,
        "dropout": 0.2321515897216631,
        "duration": 1722696703041,
        "lr": 0.11970148614599027,
        "momentum": 0.18932592661251813,
        "transform": "echo_256_flip",
        "uid": "6b054069175ca2e34f52d0eea8b5d4a2"
    },
    {
        "accuracy": 0.3576,
        "batch": 4,
        "dropout": 0.46768320758014836,
        "duration": 3595757943972,
        "lr": 0.1385127900979834,
        "momentum": 0.730333707370253,
        "transform": "echo_64_flip",
        "uid": "46b61df7f9373439a69ca8f4a122a5b3"
    }
]