[
    {
        "accuracy": 0.9728,
        "batch": 16,
        "dropout": 0.1812824751258667,
        "duration": 699846388762,
        "lr": 0.01953875392968194,
        "momentum": 0.9200174615419898,
        "transform": "soft_pad",
        "uid": "31ec5a433bc02aab40b18b9c9f8957fa"
    },
    {
        "accuracy": 0.9295,
        "batch": 16,
        "dropout": 0.1951567648298303,
        "duration": 25564560733,
        "lr": 0.0016811353500290388,
        "momentum": 0.3312707943138754,
        "transform": "echo_128",
        "uid": "d68b150d09aa8bc816c7312cf1b6e427"
    },
    {
        "accuracy": 0.9127,
        "batch": 8,
        "dropout": 0.021546711163665244,
        "duration": 45964963624,
        "lr": 0.0009139987536591001,
        "momentum": 0.727289642400692,
        "transform": "norm_64_flip",
        "uid": "eb3f59765dd9c91bae0db1e0f1209074"
    },
    {
        "accuracy": 0.907,
        "batch": 4,
        "dropout": 0.4383130498902125,
        "duration": 269101308684,
        "lr": 0.022955829366734255,
        "momentum": 0.2589295512143598,
        "transform": "echo_512_flip",
        "uid": "393aebf39740b7a846035c1c2a8ebdc7"
    },
    {
        "accuracy": 0.805,
        "batch": 2,
        "dropout": 0.006665055395155328,
        "duration": 172098248658,
        "lr": 0.00011557556478020359,
        "momentum": 0.5376339650733036,
        "transform": "norm_64",
        "uid": "37e1c47c596b572f7241e6e5ec93b383"
    },
    {
        "accuracy": 0.7243,
        "batch": 1,
        "dropout": 0.18441357717829832,
        "duration": 3683148804179,
        "lr": 0.002126630495500805,
        "momentum": 0.005725951029414866,
        "transform": "echo_512_flip",
        "uid": "02e3ee0c5c2eaf2c6da04df37b11674b"
    },
    {
        "accuracy": 0.6259,
        "batch": 64,
        "dropout": 0.22868918285127882,
        "duration": 62492417841,
        "lr": 0.004675570361913009,
        "momentum": 0.24636737013491083,
        "transform": "norm_256",
        "uid": "cede2c38d46156c113f3bbaeb82ec836"
    },
    {
        "accuracy": 0.6074,
        "batch": 32,
        "dropout": 0.14248445769083906,
        "duration": 11930522295,
        "lr": 0.00017736061855049158,
        "momentum": 0.7748044698672162,
        "transform": "norm_flip",
        "uid": "95086a2d7ebb02564d2e459a3a1c32de"
    },
    {
        "accuracy": 0.5909,
        "batch": 128,
        "dropout": 0.021034376283572298,
        "duration": 67308167307,
        "lr": 0.00686761823444196,
        "momentum": 0.3779229408804494,
        "transform": "norm_256",
        "uid": "ad7e860d63f48184631a6c9c1dd02975"
    },
    {
        "accuracy": 0.5154,
        "batch": 32,
        "dropout": 0.1771451441442079,
        "duration": 59230970582,
        "lr": 0.0011844903412254442,
        "momentum": 0.7113525561834145,
        "transform": "norm_256_flip",
        "uid": "b26a6115daa68e707828bd50847aed0c"
    },
    {
        "accuracy": 0.5081,
        "batch": 4,
        "dropout": 0.03996774037541695,
        "duration": 90172023333,
        "lr": 1.9407273207090868e-05,
        "momentum": 0.9275391413973322,
        "transform": "echo_128_flip",
        "uid": "e2645da883c88e449eb3f0204cc8956d"
    },
    {
        "accuracy": 0.3908,
        "batch": 2048,
        "dropout": 0.37795304043733224,
        "duration": 4438488890,
        "lr": 0.010576522108116156,
        "momentum": 0.6139767187942891,
        "transform": "norm_flip",
        "uid": "341a7b55562ae2732cd60680b606cec3"
    },
    {
        "accuracy": 0.3101,
        "batch": 16,
        "dropout": 0.012805983890459172,
        "duration": 23308356387,
        "lr": 7.13890997663527e-05,
        "momentum": 0.15913608157746328,
        "transform": "norm_32",
        "uid": "ec8afb11ff372e6e5458be96ada95242"
    },
    {
        "accuracy": 0.2441,
        "batch": 8,
        "dropout": 0.16340182850412138,
        "duration": 254538477409,
        "lr": 3.888653747261709e-05,
        "momentum": 0.9309288347923478,
        "transform": "norm_512",
        "uid": "8a1b7420a0c2635aea6a2f89b154a1e8"
    },
    {
        "accuracy": 0.1732,
        "batch": 8,
        "dropout": 0.3519121869061383,
        "duration": 94188489441,
        "lr": 1.0264003415981763e-05,
        "momentum": 0.028044790748382065,
        "transform": "echo_64_flip",
        "uid": "6f1189f8691daf8ea8c8fe72add4d0f7"
    }
]