[
    {
        "accuracy": 0.2680705189704895,
        "batch": 16,
        "dropout": 0.10148267926813698,
        "duration": 34709238700901,
        "lr": 0.0009089473075090423,
        "momentum": 0.6340922695592316,
        "transform": "echo_512",
        "uid": "233b79a0-7bf4-4a40-9273-436036304686"
    },
    {
        "accuracy": 0.14841462671756744,
        "batch": 16,
        "dropout": 0.12569207354106238,
        "duration": 7055036878113,
        "lr": 0.0013549286741763376,
        "momentum": 0.06081881198903272,
        "transform": "echo_32",
        "uid": "fb78b007-a1d5-466d-bfec-a8cbb1f59ab5"
    },
    {
        "accuracy": 0.145668625831604,
        "batch": 64,
        "dropout": 0.4163478253910008,
        "duration": 9102054338925,
        "lr": 6.598667865255653e-05,
        "momentum": 0.6110517396158153,
        "transform": "echo_256",
        "uid": "b2a36e3d-071e-48c8-90a5-aacb5c3e5806"
    }
]