[
    {
        "accuracy": 0.5006369426751592,
        "batch": 64,
        "duration": 303094068096,
        "lr": 0.11580356882465405,
        "momentum": 0.21098066035778573,
        "transform": "echo_32_flip",
        "uid": "24a2797e-e6fb-4bba-a25c-f6aadf65cb27"
    },
    {
        "accuracy": 0.4810191082802548,
        "batch": 64,
        "duration": 302209113334,
        "lr": 0.09426337803972393,
        "momentum": 0.2539760961070986,
        "transform": "echo_32_flip",
        "uid": "30058ead-e7c9-49c8-a131-0c4b014cc69d"
    }
]