[
    {
        "accuracy": 0.49477707006369426,
        "batch": 64,
        "duration": 407582970789,
        "lr": 0.11580356882465405,
        "momentum": 0.21098066035778573,
        "transform": "echo_32_flip",
        "uid": "43df4e90-7395-482e-a86d-70fd2d14d821"
    },
    {
        "accuracy": 0.48203821656050955,
        "batch": 64,
        "duration": 406789403017,
        "lr": 0.09426337803972393,
        "momentum": 0.2539760961070986,
        "transform": "echo_32_flip",
        "uid": "4f543ab7-b15f-4da1-867a-40769a2d1fed"
    }
]