[
    {
        "accuracy": 0.9627792806332031,
        "batch": 8,
        "duration": 896590191258,
        "lr": 0.011903043802623886,
        "momentum": 0.6355760489580419,
        "transform": "norm_32",
        "uid": "d8c396223c2c3cce2f586d70f72682b7"
    },
    {
        "accuracy": 0.9517583408476105,
        "batch": 128,
        "duration": 268299133666,
        "lr": 0.0032158120969165934,
        "momentum": 0.8642734067373531,
        "transform": "norm_32_flip",
        "uid": "e7a394b2a8fe1e5e57f9d613e8a29557"
    },
    {
        "accuracy": 0.9192465684801122,
        "batch": 32,
        "duration": 403556765131,
        "lr": 0.00014181177632041712,
        "momentum": 0.877130939288459,
        "transform": "norm_32",
        "uid": "ad293b72f0741ca219a949e919fa4e37"
    },
    {
        "accuracy": 0.8167518284741008,
        "batch": 8,
        "duration": 819933804814,
        "lr": 9.331195053432772e-05,
        "momentum": 0.7074302042817451,
        "transform": "echo_32_flip",
        "uid": "f4a034d200a005e3941547cb3a20f712"
    }
]