[
    {
        "accuracy": 0.7444585987261146,
        "batch": 2,
        "dropout": 0.29977899507954886,
        "duration": 473626454982,
        "lr": 0.00986717558406419,
        "momentum": 0.36577442041305996,
        "transform": "norm_512_flip",
        "uid": "d226995d-e367-496a-8e4c-daa0a828ec82"
    },
    {
        "accuracy": 0.7207643312101911,
        "batch": 1,
        "dropout": 0.3415854257532225,
        "duration": 532422646232,
        "lr": 0.02163106279896229,
        "momentum": 0.5543410632774255,
        "transform": "norm_299_flip",
        "uid": "3dd6b682-309a-4979-a53c-34dd1d6a4f29"
    },
    {
        "accuracy": 0.6226751592356687,
        "batch": 16,
        "dropout": 0.1258997373546598,
        "duration": 365116305933,
        "lr": 0.004804958076548357,
        "momentum": 0.8691100224579109,
        "transform": "echo_512_flip",
        "uid": "d98730db-76f4-4361-98e7-f4a591e93bcd"
    }
]