[
    {
        "accuracy": 0.613515679791604,
        "batch": 4096,
        "dropout": 0.06626719605550624,
        "duration": 1319583340550,
        "lr": 0.0002560180940381642,
        "momentum": 0.42094805492339815,
        "transform": "echo_64_flip",
        "uid": "e54200ea0551c0ce07997366b81c3ebb"
    },
    {
        "accuracy": 0.613515679791604,
        "batch": 8,
        "dropout": 0.0779452342351537,
        "duration": 3252893383424,
        "lr": 0.12750833163610134,
        "momentum": 0.7034268025265779,
        "transform": "echo_flip",
        "uid": "41ef9841572a4a3b30753cdec5831354"
    },
    {
        "accuracy": 0.613515679791604,
        "batch": 4,
        "dropout": 0.43634321776825813,
        "duration": 6923231893328,
        "lr": 0.5319219195529741,
        "momentum": 0.08701463441884816,
        "transform": "norm_299_flip",
        "uid": "fe05c0bd31f3574a2945209e04c0770c"
    }
]