[
    {
        "accuracy": 0.2376,
        "batch": 256,
        "duration": 714987822974,
        "lr": 0.0008367883897273635,
        "momentum": 0.9356348351544213,
        "transform": "norm_299_flip",
        "uid": "9d072bff-e056-4303-a6c1-9b28a763d26f"
    },
    {
        "accuracy": 0.0356,
        "batch": 2,
        "duration": 1316377484948,
        "lr": 3.5796779916018426e-05,
        "momentum": 0.4169031398126447,
        "transform": "echo_256_flip",
        "uid": "5742a84f-b7e1-4e85-b20d-e288a1bab417"
    }
]