[
    {
        "accuracy": 0.6784,
        "batch": 64,
        "duration": 32652281792,
        "lr": 0.01837591076380729,
        "momentum": 0.7299280796919108,
        "transform": "complex",
        "uid": "d7837898-5c49-492b-87b4-a5862bac2012"
    },
    {
        "accuracy": 0.6143,
        "batch": 256,
        "duration": 12151459852,
        "lr": 0.033538242669642476,
        "momentum": 0.7423372733678091,
        "transform": "complex",
        "uid": "cf5dd449-8646-46ea-9dfb-a7c325065930"
    },
    {
        "accuracy": 0.6061,
        "batch": 16,
        "duration": 121353457512,
        "lr": 0.00045389180019338415,
        "momentum": 0.8929252318727656,
        "transform": "complex",
        "uid": "1e718f51-1fe0-4b1c-a4af-c6526e7e6097"
    },
    {
        "accuracy": 0.5995,
        "batch": 4,
        "duration": 4516575701762,
        "lr": 0.0018668638946480753,
        "momentum": 0.8904350145518335,
        "transform": "complex_512",
        "uid": "a16835f9-36e7-4939-8647-5bf3d39fa954"
    },
    {
        "accuracy": 0.3848,
        "batch": 2,
        "duration": 915456951082,
        "lr": 4.261495202688059e-05,
        "momentum": 0.358172522615803,
        "transform": "complex",
        "uid": "84811a25-eef5-483c-9de9-226ebbb53657"
    }
]