[
    {
        "accuracy": 0.7769,
        "batch": 4,
        "dropout": 0.5,
        "duration": 1373473813276,
        "lr": 0.0061,
        "momentum": 0.7549,
        "transform": "norm_299",
        "uid": "bd2714f0eb66d279a7b37ad6564e45d2"
    },
    {
        "accuracy": 0.7565,
        "batch": 32,
        "dropout": 0.2919445486947473,
        "duration": 746775063393,
        "lr": 0.03909315042977872,
        "momentum": 0.357363211662744,
        "transform": "norm_256",
        "uid": "e83df2954a251f65133ab137a83a4ad7"
    }
]