[
    {
        "accuracy": 0.9562669071235347,
        "batch": 16,
        "duration": 15883728129190,
        "lr": 0.16636678987796136,
        "momentum": 0.5609255057529814,
        "transform": "norm_299_flip",
        "uid": "1b4a0d36-d230-4e8a-8546-f7ff483430ab"
    },
    {
        "accuracy": 0.9242560865644724,
        "batch": 4096,
        "duration": 1019076350460,
        "lr": 0.013444742671859524,
        "momentum": 0.7447457688057652,
        "transform": "norm_32_flip",
        "uid": "57171097-9c99-42ee-965d-8b1219d51559"
    }
]