[
    {
        "accuracy": 0.9871,
        "attention_dropout": 0.121092243977593,
        "batch": 4,
        "dropout": 0.3821245874311294,
        "duration": 10518177123474,
        "lr": 0.030294730795046333,
        "momentum": 0.03172770661797619,
        "stochastic_depth_prob": 0.9742369105000677,
        "transform": "echo_flip",
        "uid": "7212cc80-eb5b-45bb-a89b-d50287fd566a"
    },
    {
        "accuracy": 0.9772,
        "attention_dropout": 0.8012805575611412,
        "batch": 8,
        "dropout": 0.3007062229275218,
        "duration": 5227163924687,
        "lr": 0.47633241241294516,
        "momentum": 0.2568860758586341,
        "stochastic_depth_prob": 0.26774915693124246,
        "transform": "echo_64",
        "uid": "6e80c2d6-882c-4353-8ca2-286e9bb5c629"
    }
]