[
    {
        "accuracy": 0.3125,
        "batch": 16,
        "duration": 4705181226167,
        "lr": 0.0049134941270017225,
        "momentum": 0.4718387645077645,
        "transform": "complex_512_flip",
        "uid": "3f265d8d5bbfeccce97de19ac4b57e2f"
    },
    {
        "accuracy": 0.2417,
        "batch": 32,
        "duration": 222819466457,
        "lr": 0.0001506953589852698,
        "momentum": 0.8435440906009839,
        "transform": "complex_128",
        "uid": "105baa0bc5a5b317892423936e8e7e06"
    },
    {
        "accuracy": 0.1738,
        "batch": 4096,
        "duration": 66403469870,
        "lr": 0.13223329090535238,
        "momentum": 0.9512588179443766,
        "transform": "complex_64",
        "uid": "a1ec2e40be229c812e5d2f4ca744d054"
    }
]